{"card":{"id":1017391,"name":"Goku (Xeno)","character_id":983,"character_size":4,"cost":32,"rarity":4,"hp_init":6311,"hp_max":6635,"atk_init":6789,"atk_max":7510,"def_init":3405,"def_max":3567,"element":14,"special_motion":1,"passive_skill_set_id":1550,"potential_board_id":24,"leader_skill_set_id":101739,"eball_mod_min":40,"eball_mod_num100":4,"eball_mod_mid":0,"eball_mod_mid_num":0,"eball_mod_max":130,"eball_mod_max_num":12,"open_at":"2019-08-13 06:30:00","title":"Mission to Protect History","leader_skill":"\"Goku's Family\" Category \nKi +3 and HP, ATK & DEF +90%","passive_skill_name":"Allies' Support","passive_skill_desc":"ATK & DEF +77%; \n\"Goku's Family\" Category allies' \nKi +2 and ATK & DEF +30%","skill_level_max":10,"is_f2p":false,"unique_info_id":487,"is_dokkan_fes":false,"is_carnival_only":false,"passive_skill_itemized_desc":"*Basic effect(s)*\n- ATK & DEF 77%{passiveImg:up_g}\n- \"Goku's Family\" Category allies' Ki +2 and ATK & DEF 30%{passiveImg:up_g}"},"categories":[{"id":17,"name":"Pure Saiyans","priority":80000},{"id":26,"name":"Time Travelers","priority":29500},{"id":30,"name":"Goku's Family","priority":79400},{"id":39,"name":"Kamehameha","priority":69200},{"id":42,"name":"Dragon Ball Heroes","priority":9900},{"id":61,"name":"Crossover","priority":10000},{"id":65,"name":"Turtle School","priority":39100},{"id":70,"name":"Defenders of Justice","priority":29000},{"id":87,"name":"Bond of Parent and Child","priority":49750},{"id":89,"name":"Earth-Bred Fighters","priority":30000}],"potential":[{"atk":2000,"def":2000,"hp":2000},{"atk":3700,"def":3300,"hp":4100},{"atk":4000,"def":3600,"hp":4400},{"atk":4700,"def":3910,"hp":4710},{"atk":5000,"def":4600,"hp":5400}],"specials":[{"id":1810,"name":"Kamehameha","description":"Raises ATK and \ncauses supreme damage to enemy","aim_target":0,"increase_rate":120,"lv_bonus":20,"style":"Normal","lv_start":0,"eball_num_start":12,"card_costume_condition_id":0,"special_category_id":1,"special_category_name":"Ki Blast","special_view_id":5261,"special_view_id_has_ko":false,"bonus_view_id_1":0,"bonus_view_id_2":0,"bonus_view_id_1_has_ko":false,"bonus_view_id_2_has_ko":false,"special_bonus_1_lv":0,"special_bonus_2_lv":0}],"awakening_routes":[{"awaked_card_id":1017390,"awaked_card":{"id":1017390,"name":"Goku (Xeno)","title":"Mission to Protect History","element":4,"rarity":3,"open_at":"2019-08-13 06:30:00","base_id":1017390,"awaken_items":null,"awaken_cost":0}},{"card_id":1017390,"awaked_card_id":1017391,"awaked_card":{"type":"CardAwakeningRoute::Zet","id":1017391,"name":"Goku (Xeno)","title":"Mission to Protect History","element":14,"rarity":4,"open_at":"2019-08-13 06:30:00","base_id":1017390,"awaken_items":[{"item_id":1,"quantity":50,"rarity":0,"name":"Gregory","description":"A common, easily obtained Awakening Medal.","zeni":500},{"item_id":7,"quantity":20,"rarity":1,"name":"Mutaito","description":"A Medal required primarily for PHY Awakening.\nRelatively easy to get.","zeni":5000},{"item_id":10,"quantity":10,"rarity":2,"name":"Grand Elder Guru","description":"A Medal required primarily for PHY Awakening.\nSomewhat difficult to get.","zeni":50000},{"item_id":17,"quantity":3,"rarity":3,"name":"East Kai","description":"A Medal required primarily for PHY Awakening.\nDifficult to get.","zeni":250000},{"item_id":19,"quantity":1,"rarity":3,"name":"Supreme Kai","description":"The ultimate, rarely obtainable Awakening Medal.","zeni":500000}],"awaken_cost":1875000}},{"card_id":1017391,"awaked_card_id":1023301,"awaked_card":{"type":"CardAwakeningRoute::Dokkan","id":1023301,"name":"Super Saiyan Goku (Xeno)","title":"Fierce Battle for Space and Time","element":14,"rarity":4,"open_at":"2021-11-25 08:00:00","base_id":1023300,"awaken_items":[{"item_id":21201,"quantity":20,"rarity":3,"name":"Mechikabura","description":"Character-specific Medal required for Awakening.","zeni":20000}],"awaken_cost":400000}}],"transformations":[{"next_card_id":1017391,"next_card":{"id":1017391,"name":"Goku (Xeno)","rarity":4,"element":14,"open_at":"2019-08-13 06:30:00","base_id":1017390}}],"costumes":[],"card_links":[{"idx":1,"link_skill_id":22,"name":"Saiyan Warrior Race","level1_description":"ATK +5%","level10_description":"ATK +10%"},{"idx":2,"link_skill_id":34,"name":"The Saiyan Lineage","level1_description":"Ki +1","level10_description":"Ki +2 and ATK & DEF +5%"},{"idx":3,"link_skill_id":47,"name":"Kamehameha","level1_description":"ATK +5% when performing a Super Attack","level10_description":"ATK +10% when performing a Super Attack"},{"idx":4,"link_skill_id":69,"name":"Patrol","level1_description":"Ki +2","level10_description":"Ki +2 and DEF +20%"},{"idx":5,"link_skill_id":30,"name":"Experienced Fighters","level1_description":"ATK +10%","level10_description":"ATK +15%"},{"idx":6,"link_skill_id":97,"name":"Prepared for Battle","level1_description":"Ki +2","level10_description":"Ki +2 and ATK & DEF +5%"}],"partners":[{"id":1023301,"name":"Super Saiyan Goku (Xeno)","title":"Fierce Battle for Space and Time","rarity":4,"element":14,"base_id":1023300,"common_link_count":5,"common_links":[30,34,47,69,97],"common_categories":[17,26,30,39,42,61,65,70,87,89],"is_same_element":true,"is_same_base_element":true,"is_same_element_group":true,"common_team_count":13,"has_eza":true,"has_sticker":true,"has_super_eza":false},{"id":1030401,"name":"Goku","title":"A Fight for the Ages","rarity":4,"element":10,"base_id":1030400,"common_link_count":5,"common_links":[22,30,34,47,97],"common_categories":[17,30,39,65,87,89],"is_same_element":false,"is_same_base_element":false,"is_same_element_group":true,"common_team_count":7,"has_eza":false,"has_sticker":false,"has_super_eza":false},{"id":1022351,"name":"Goku & Vegeta","title":"Spirited Challenge","rarity":4,"element":11,"base_id":1022350,"common_link_count":5,"common_links":[22,30,34,47,97],"common_categories":[17,39,87],"is_same_element":false,"is_same_base_element":false,"is_same_element_group":true,"common_team_count":4,"has_eza":false,"has_sticker":false,"has_super_eza":false},{"id":1025311,"name":"Super Full Power Saiyan 4 Limit Breaker Goku (Xeno)","title":"Breaking Limits for Victory","rarity":4,"element":12,"base_id":1025310,"common_link_count":4,"common_links":[22,30,47,97],"common_categories":[17,26,30,39,42,61,65,70,87,89],"is_same_element":false,"is_same_base_element":false,"is_same_element_group":true,"common_team_count":11,"has_eza":false,"has_sticker":false,"has_super_eza":false},{"id":1030671,"name":"Goku (Mini) (DAIMA)","title":"Companion from the Old Days","rarity":4,"element":14,"base_id":1030670,"common_link_count":4,"common_links":[22,30,34,97],"common_categories":[17,30,39,65,87,89],"is_same_element":true,"is_same_base_element":true,"is_same_element_group":true,"common_team_count":9,"has_eza":false,"has_sticker":false,"has_super_eza":false},{"id":1023461,"name":"Super Saiyan 2 Goku","title":"Battle to Protect Tomorrow","rarity":4,"element":14,"base_id":1023460,"common_link_count":4,"common_links":[22,30,34,97],"common_categories":[17,30,39,65,87,89],"is_same_element":true,"is_same_base_element":true,"is_same_element_group":true,"common_team_count":9,"has_eza":true,"has_sticker":true,"has_super_eza":false},{"id":1030141,"name":"Warrior in Black (Super Saiyan) (Dark Dragon Ball Boost)","title":"Enigmatic Fighter","rarity":4,"element":14,"base_id":1030140,"common_link_count":4,"common_links":[22,30,34,97],"common_categories":[17,26,30,42,61,87],"is_same_element":true,"is_same_base_element":true,"is_same_element_group":true,"common_team_count":9,"has_eza":false,"has_sticker":false,"has_super_eza":false},{"id":1019861,"name":"Goku (Angel)","title":"Passing the Mantle","rarity":4,"element":14,"base_id":1019860,"common_link_count":4,"common_links":[22,30,34,47],"common_categories":[17,30,39,65,87,89],"is_same_element":true,"is_same_base_element":true,"is_same_element_group":true,"common_team_count":9,"has_eza":true,"has_sticker":true,"has_super_eza":false},{"id":1021491,"name":"Goku (Dokkan Butoden)","title":"All-Out Showdown!","rarity":4,"element":14,"base_id":1021490,"common_link_count":4,"common_links":[22,34,47,97],"common_categories":[17,30,39,65,87,89],"is_same_element":true,"is_same_base_element":true,"is_same_element_group":true,"common_team_count":9,"has_eza":true,"has_sticker":true,"has_super_eza":false},{"id":1012331,"name":"Super Saiyan God SS Goku","title":"Drive to Win","rarity":4,"element":13,"base_id":1012330,"common_link_count":4,"common_links":[22,34,47,97],"common_categories":[17,26,30,39,65,87,89],"is_same_element":false,"is_same_base_element":false,"is_same_element_group":true,"common_team_count":8,"has_eza":true,"has_sticker":true,"has_super_eza":false},{"id":1025351,"name":"Super Saiyan 4 Gohan","title":"Power to Protect the Cherished","rarity":4,"element":12,"base_id":1025350,"common_link_count":4,"common_links":[22,30,34,97],"common_categories":[26,30,42,61,70,87,89],"is_same_element":false,"is_same_base_element":false,"is_same_element_group":true,"common_team_count":8,"has_eza":false,"has_sticker":false,"has_super_eza":false},{"id":1023061,"name":"Super Saiyan Goku","title":"Caught Between Illness and Adversary","rarity":4,"element":14,"base_id":1023060,"common_link_count":4,"common_links":[22,30,34,97],"common_categories":[17,30,65,87,89],"is_same_element":true,"is_same_base_element":true,"is_same_element_group":true,"common_team_count":8,"has_eza":false,"has_sticker":false,"has_super_eza":false},{"id":1017721,"name":"Super Saiyan Goku","title":"Unwavering Will and Newfound Power","rarity":4,"element":12,"base_id":1017720,"common_link_count":4,"common_links":[22,30,34,47],"common_categories":[17,30,39,65,87,89],"is_same_element":false,"is_same_base_element":false,"is_same_element_group":true,"common_team_count":7,"has_eza":true,"has_sticker":true,"has_super_eza":false},{"id":4020631,"name":"Goku","title":"Resolve for the Final Battle","rarity":4,"element":12,"base_id":4020630,"common_link_count":4,"common_links":[22,30,34,97],"common_categories":[17,30,39,65,87,89],"is_same_element":false,"is_same_base_element":false,"is_same_element_group":true,"common_team_count":7,"has_eza":true,"has_sticker":false,"has_super_eza":false},{"id":1016101,"name":"Super Saiyan God SS Goku","title":"Becoming a Furious God","rarity":4,"element":10,"base_id":1016100,"common_link_count":4,"common_links":[22,30,47,97],"common_categories":[17,30,39,65,87,89],"is_same_element":false,"is_same_base_element":false,"is_same_element_group":true,"common_team_count":7,"has_eza":true,"has_sticker":true,"has_super_eza":false},{"id":1008371,"name":"Goku","title":"Infinite Curiosity","rarity":4,"element":12,"base_id":1008370,"common_link_count":4,"common_links":[22,30,34,47],"common_categories":[17,30,39,65,87,89],"is_same_element":false,"is_same_base_element":false,"is_same_element_group":true,"common_team_count":7,"has_eza":false,"has_sticker":false,"has_super_eza":false},{"id":1019141,"name":"Bardock","title":"Raging Counterattack","rarity":4,"element":10,"base_id":1019140,"common_link_count":4,"common_links":[22,30,34,97],"common_categories":[17,26,30,61,87],"is_same_element":false,"is_same_base_element":false,"is_same_element_group":true,"common_team_count":6,"has_eza":true,"has_sticker":true,"has_super_eza":false},{"id":1014491,"name":"Goku (GT)","title":"Victory Clincher","rarity":4,"element":13,"base_id":1014490,"common_link_count":4,"common_links":[22,30,34,97],"common_categories":[17,30,65,87,89],"is_same_element":false,"is_same_base_element":false,"is_same_element_group":true,"common_team_count":6,"has_eza":true,"has_sticker":true,"has_super_eza":false},{"id":1025021,"name":"Goku","title":"Culmination of Thousands of Thoughts","rarity":4,"element":12,"base_id":1025020,"common_link_count":4,"common_links":[22,30,34,97],"common_categories":[17,30,65,87,89],"is_same_element":false,"is_same_base_element":false,"is_same_element_group":true,"common_team_count":6,"has_eza":false,"has_sticker":false,"has_super_eza":false},{"id":1030211,"name":"Goten (Kid) & Icarus Jr.","title":"Cheerful Young Ones","rarity":4,"element":12,"base_id":1030210,"common_link_count":4,"common_links":[22,34,47,97],"common_categories":[30,39,87,89],"is_same_element":false,"is_same_base_element":false,"is_same_element_group":true,"common_team_count":5,"has_eza":false,"has_sticker":false,"has_super_eza":false},{"id":4025741,"name":"Goku & Vegeta","title":"Universe's Last Hope","rarity":5,"element":14,"base_id":4025740,"common_link_count":4,"common_links":[22,30,34,97],"common_categories":[17,87],"is_same_element":true,"is_same_base_element":true,"is_same_element_group":true,"common_team_count":5,"has_eza":false,"has_sticker":false,"has_super_eza":false},{"id":1030681,"name":"Vegeta (Mini) (DAIMA)","title":"Stable Combat Power","rarity":4,"element":12,"base_id":1030680,"common_link_count":4,"common_links":[22,30,34,97],"common_categories":[17,26,87],"is_same_element":false,"is_same_base_element":false,"is_same_element_group":true,"common_team_count":4,"has_eza":false,"has_sticker":false,"has_super_eza":false},{"id":1022191,"name":"Goku (Angel) & Vegeta (Angel)","title":"Fusion Reborn","rarity":5,"element":11,"base_id":1022190,"common_link_count":4,"common_links":[22,30,34,97],"common_categories":[17,39,87],"is_same_element":false,"is_same_base_element":false,"is_same_element_group":true,"common_team_count":4,"has_eza":true,"has_sticker":false,"has_super_eza":false},{"id":1019041,"name":"Bardock & Gine","title":"Parents' Guidance","rarity":4,"element":13,"base_id":1019040,"common_link_count":4,"common_links":[22,30,34,97],"common_categories":[17,30,87],"is_same_element":false,"is_same_base_element":false,"is_same_element_group":true,"common_team_count":4,"has_eza":true,"has_sticker":true,"has_super_eza":false},{"id":1020461,"name":"Goku & Vegeta (Angel)","title":"Fused Hope","rarity":5,"element":13,"base_id":1020460,"common_link_count":4,"common_links":[22,30,34,97],"common_categories":[17,39,87],"is_same_element":false,"is_same_base_element":false,"is_same_element_group":true,"common_team_count":4,"has_eza":true,"has_sticker":false,"has_super_eza":false}],"sa_level_cards":[],"finish_skills":[],"standby_skills":[]}