{
  "name": "Golden Frieza (Angel) & Android #17",
  "id": 1021431,
  "hp_max": 20725,
  "atk_max": 15700,
  "def_max": 7638,
  "is_f2p": false,
  "is_dokkan_fes": false,
  "is_carnival_only": false,
  "open_at": "2021-07-26 05:00:00",
  "has_optimal_awakening_growths": true,
  "class": "Extreme",
  "type": "PHY",
  "categories": [
    {
      "id": 6,
      "name": "Universe Survival Saga",
      "priority": 89500
    },
    {
      "id": 28,
      "name": "Joined Forces",
      "priority": 49800
    },
    {
      "id": 22,
      "name": "Representatives of Universe 7",
      "priority": 39700
    },
    {
      "id": 91,
      "name": "Tournament Participants",
      "priority": 38900
    },
    {
      "id": 58,
      "name": "Battle of Wits",
      "priority": 19100
    },
    {
      "id": 83,
      "name": "Battle of Fate",
      "priority": 18950
    }
  ]
}