{
  "name": "Trunks (Kid)",
  "id": 1022011,
  "hp_max": 7042,
  "atk_max": 8397,
  "def_max": 4111,
  "is_f2p": true,
  "is_dokkan_fes": false,
  "is_carnival_only": false,
  "open_at": "2021-06-21 06:30:00",
  "has_optimal_awakening_growths": true,
  "class": "Super",
  "type": "TEQ",
  "active_skill_id": -1,
  "entree_id": -1,
  "fukkatsu_id": -1,
  "standby_id": -1,
  "finish_1_id": -1,
  "finish_2_id": -1,
  "transfo_id": -1,
  "categories": [
    {
      "id": 5,
      "name": "Hybrid Saiyans",
      "priority": 79900
    },
    {
      "id": 31,
      "name": "Vegeta's Family",
      "priority": 79300
    },
    {
      "id": 33,
      "name": "Youth",
      "priority": 79100
    },
    {
      "id": 87,
      "name": "Bond of Parent and Child",
      "priority": 49750
    },
    {
      "id": 79,
      "name": "Bond of Friendship",
      "priority": 49600
    },
    {
      "id": 29,
      "name": "Movie Heroes",
      "priority": 39300
    },
    {
      "id": 89,
      "name": "Earth-Bred Fighters",
      "priority": 30000
    },
    {
      "id": 68,
      "name": "Gifted Warriors",
      "priority": 29900
    },
    {
      "id": 81,
      "name": "Entrusted Will",
      "priority": 19300
    }
  ]
}