{"card":{"id":1007421,"name":"Super Paikuhan","character_id":559,"character_size":4,"cost":27,"rarity":4,"hp_init":7147,"hp_max":8497,"atk_init":6611,"atk_max":7873,"def_init":3575,"def_max":4197,"element":13,"special_motion":1,"passive_skill_set_id":674,"potential_board_id":23,"leader_skill_set_id":100742,"eball_mod_min":40,"eball_mod_num100":4,"eball_mod_mid":0,"eball_mod_mid_num":0,"eball_mod_max":130,"eball_mod_max_num":12,"open_at":"2019-08-13 06:30:00","title":"Mastered Skills","leader_skill":"All Types HP & ATK +20%","passive_skill_name":"Unmissable Chance","passive_skill_desc":"ATK +10000 when facing only 1 enemy","skill_level_max":10,"is_f2p":false,"unique_info_id":291,"is_dokkan_fes":false,"is_carnival_only":false,"passive_skill_itemized_desc":"*When facing only 1 enemy*\n- ATK 10000{passiveImg:up_g}"},"categories":[{"id":37,"name":"Worthy Rivals","priority":50000},{"id":42,"name":"Dragon Ball Heroes","priority":9900},{"id":58,"name":"Battle of Wits","priority":19100},{"id":61,"name":"Crossover","priority":10000},{"id":71,"name":"Storied Figures","priority":29300}],"potential":[{"atk":2000,"def":2000,"hp":2000},{"atk":4100,"def":3300,"hp":3700},{"atk":4400,"def":3600,"hp":4000},{"atk":5100,"def":3910,"hp":4310},{"atk":5400,"def":4600,"hp":5000}],"specials":[{"id":450,"name":"Thunder Flash","description":"Causes supreme damage to enemy \nand greatly lowers ATK","aim_target":0,"increase_rate":150,"lv_bonus":20,"style":"Normal","lv_start":0,"eball_num_start":12,"card_costume_condition_id":0,"special_category_id":1,"special_category_name":"Ki Blast","special_view_id":1539,"special_view_id_has_ko":false,"bonus_view_id_1":0,"bonus_view_id_2":0,"bonus_view_id_1_has_ko":false,"bonus_view_id_2_has_ko":false,"special_bonus_1_lv":0,"special_bonus_2_lv":0}],"awakening_routes":[{"awaked_card_id":1007420,"awaked_card":{"id":1007420,"name":"Super Paikuhan","title":"Mastered Skills","element":3,"rarity":3,"open_at":"2019-08-13 06:30:00","base_id":1007420,"awaken_items":null,"awaken_cost":0}},{"card_id":1007420,"awaked_card_id":1007421,"awaked_card":{"type":"CardAwakeningRoute::Zet","id":1007421,"name":"Super Paikuhan","title":"Mastered Skills","element":13,"rarity":4,"open_at":"2019-08-13 06:30:00","base_id":1007420,"awaken_items":[{"item_id":1,"quantity":50,"rarity":0,"name":"Gregory","description":"A common, easily obtained Awakening Medal.","zeni":500},{"item_id":6,"quantity":20,"rarity":1,"name":"Master Roshi","description":"A Medal required primarily for STR Awakening.\nRelatively easy to get.","zeni":5000},{"item_id":12,"quantity":10,"rarity":2,"name":"Bibidi","description":"A Medal required primarily for STR Awakening.\nSomewhat difficult to get.","zeni":50000},{"item_id":16,"quantity":3,"rarity":3,"name":"South Kai","description":"A Medal required primarily for STR Awakening.\nDifficult to get.","zeni":250000},{"item_id":20,"quantity":1,"rarity":3,"name":"Elder Kai","description":"The ultimate, rarely obtainable Awakening Medal.","zeni":500000}],"awaken_cost":1875000}},{"card_id":1007421,"awaked_card_id":1016751,"awaked_card":{"type":"CardAwakeningRoute::Dokkan","id":1016751,"name":"Super Paikuhan","title":"Intensely Trained Body and Mind","element":13,"rarity":4,"open_at":"2019-08-13 06:30:00","base_id":1016750,"awaken_items":[{"item_id":18103,"quantity":20,"rarity":3,"name":"Supreme Kai of Time","description":"Character-specific Medal required for Awakening.","zeni":20000}],"awaken_cost":400000}}],"transformations":[{"next_card_id":1007421,"next_card":{"id":1007421,"name":"Super Paikuhan","rarity":4,"element":13,"open_at":"2019-08-13 06:30:00","base_id":1007420}}],"costumes":[],"card_links":[{"idx":1,"link_skill_id":17,"name":"Gentleman","level1_description":"Ki +2","level10_description":"Ki +2 and DEF +10%"},{"idx":2,"link_skill_id":8,"name":"Brainiacs","level1_description":"ATK & DEF +10%","level10_description":"ATK & DEF +15%"},{"idx":3,"link_skill_id":52,"name":"Tough as Nails","level1_description":"DEF +15%","level10_description":"DEF +20% and \nreduces damage received by 5%"},{"idx":4,"link_skill_id":60,"name":"Shocking Speed","level1_description":"Ki +2","level10_description":"Ki +2 and DEF +5%"},{"idx":5,"link_skill_id":30,"name":"Experienced Fighters","level1_description":"ATK +10%","level10_description":"ATK +15%"},{"idx":6,"link_skill_id":16,"name":"Supreme Warrior","level1_description":"Ki +1","level10_description":"Ki +2 and ATK +10%"}],"partners":[{"id":1010941,"name":"Paikuhan","title":"Clever Strategy","rarity":4,"element":11,"base_id":1010940,"common_link_count":5,"common_links":[8,17,30,52,60],"common_categories":[37,58,71],"is_same_element":false,"is_same_base_element":false,"is_same_element_group":true,"common_team_count":4,"has_eza":true,"has_sticker":true,"has_super_eza":false},{"id":1021331,"name":"Paikuhan","title":"Righteous Otherworld Defense","rarity":4,"element":10,"base_id":1021330,"common_link_count":4,"common_links":[16,17,30,60],"common_categories":[37,58,71],"is_same_element":false,"is_same_base_element":false,"is_same_element_group":true,"common_team_count":4,"has_eza":false,"has_sticker":true,"has_super_eza":false},{"id":1011041,"name":"Paikuhan","title":"Blazing Clash","rarity":4,"element":13,"base_id":1011040,"common_link_count":3,"common_links":[17,30,60],"common_categories":[37,58,71],"is_same_element":true,"is_same_base_element":true,"is_same_element_group":true,"common_team_count":6,"has_eza":false,"has_sticker":false,"has_super_eza":false},{"id":1025411,"name":"Super Hearts","title":"Ultimate Godslayer","rarity":4,"element":23,"base_id":1025410,"common_link_count":3,"common_links":[8,17,60],"common_categories":[42,58,61],"is_same_element":false,"is_same_base_element":true,"is_same_element_group":false,"common_team_count":4,"has_eza":false,"has_sticker":false,"has_super_eza":false},{"id":4025421,"name":"Ultimate Hearts","title":"Ultimate Godslayer","rarity":4,"element":23,"base_id":4025420,"common_link_count":3,"common_links":[8,17,60],"common_categories":[42,58,61],"is_same_element":false,"is_same_base_element":true,"is_same_element_group":false,"common_team_count":4,"has_eza":false,"has_sticker":false,"has_super_eza":false},{"id":1017491,"name":"Piccolo","title":"Kami and Demon King United","rarity":4,"element":14,"base_id":1017490,"common_link_count":3,"common_links":[8,30,60],"common_categories":[37,58],"is_same_element":false,"is_same_base_element":false,"is_same_element_group":true,"common_team_count":3,"has_eza":true,"has_sticker":true,"has_super_eza":false},{"id":1009231,"name":"Piccolo","title":"Budding Heart","rarity":5,"element":12,"base_id":1009230,"common_link_count":3,"common_links":[8,30,60],"common_categories":[37,58],"is_same_element":false,"is_same_base_element":false,"is_same_element_group":true,"common_team_count":3,"has_eza":true,"has_sticker":false,"has_super_eza":false},{"id":1022451,"name":"Piccolo","title":"Exceptional Wisdom","rarity":4,"element":11,"base_id":1022450,"common_link_count":3,"common_links":[8,30,60],"common_categories":[37,58],"is_same_element":false,"is_same_base_element":false,"is_same_element_group":true,"common_team_count":3,"has_eza":false,"has_sticker":false,"has_super_eza":false},{"id":4017501,"name":"Piccolo","title":"Kami and Demon King United","rarity":4,"element":14,"base_id":4017500,"common_link_count":3,"common_links":[8,30,60],"common_categories":[37,58],"is_same_element":false,"is_same_base_element":false,"is_same_element_group":true,"common_team_count":3,"has_eza":true,"has_sticker":false,"has_super_eza":false},{"id":1014681,"name":"Piccolo","title":"Battle as a Namekian","rarity":4,"element":10,"base_id":1014680,"common_link_count":3,"common_links":[8,30,60],"common_categories":[37,58],"is_same_element":false,"is_same_base_element":false,"is_same_element_group":true,"common_team_count":3,"has_eza":true,"has_sticker":true,"has_super_eza":false},{"id":4014691,"name":"Piccolo","title":"Battle as a Namekian","rarity":4,"element":10,"base_id":4014690,"common_link_count":3,"common_links":[8,30,60],"common_categories":[37,58],"is_same_element":false,"is_same_base_element":false,"is_same_element_group":true,"common_team_count":3,"has_eza":true,"has_sticker":false,"has_super_eza":false},{"id":1011211,"name":"Jackie Chun","title":"Domineering Victory Declaration","rarity":4,"element":12,"base_id":1011210,"common_link_count":3,"common_links":[8,16,17],"common_categories":[58],"is_same_element":false,"is_same_base_element":false,"is_same_element_group":true,"common_team_count":2,"has_eza":true,"has_sticker":true,"has_super_eza":false},{"id":1024141,"name":"Goku & Piccolo/Piccolo","title":"Desperate Onslaught","rarity":5,"element":14,"base_id":1024140,"common_link_count":3,"common_links":[30,52,60],"common_categories":[58],"is_same_element":false,"is_same_base_element":false,"is_same_element_group":true,"common_team_count":2,"has_eza":false,"has_sticker":false,"has_super_eza":false},{"id":4024151,"name":"Piccolo","title":"Desperate Onslaught","rarity":5,"element":14,"base_id":4024150,"common_link_count":3,"common_links":[30,52,60],"common_categories":[58],"is_same_element":false,"is_same_base_element":false,"is_same_element_group":true,"common_team_count":2,"has_eza":false,"has_sticker":false,"has_super_eza":false},{"id":1021541,"name":"Master Roshi & Tien","title":"Teamwork Across Schools","rarity":4,"element":11,"base_id":1021540,"common_link_count":3,"common_links":[8,30,52],"common_categories":[58],"is_same_element":false,"is_same_base_element":false,"is_same_element_group":true,"common_team_count":2,"has_eza":true,"has_sticker":true,"has_super_eza":false},{"id":1009051,"name":"Obotchaman","title":"Power of Politeness","rarity":4,"element":10,"base_id":1009050,"common_link_count":3,"common_links":[8,17,60],"common_categories":[61],"is_same_element":false,"is_same_base_element":false,"is_same_element_group":true,"common_team_count":2,"has_eza":false,"has_sticker":false,"has_super_eza":false},{"id":1021431,"name":"Golden Frieza (Angel) & Android #17","title":"Very Last Possibility","rarity":5,"element":24,"base_id":1021430,"common_link_count":3,"common_links":[8,52,60],"common_categories":[58],"is_same_element":false,"is_same_base_element":false,"is_same_element_group":false,"common_team_count":1,"has_eza":true,"has_sticker":false,"has_super_eza":false},{"id":1015291,"name":"Piccolo","title":"A Shot at Victory","rarity":4,"element":13,"base_id":1015290,"common_link_count":2,"common_links":[8,30],"common_categories":[37,58],"is_same_element":true,"is_same_base_element":true,"is_same_element_group":true,"common_team_count":5,"has_eza":true,"has_sticker":true,"has_super_eza":false},{"id":1024951,"name":"Piccolo","title":"Valiant Confrontation","rarity":4,"element":13,"base_id":1024950,"common_link_count":2,"common_links":[8,30],"common_categories":[37,58],"is_same_element":true,"is_same_base_element":true,"is_same_element_group":true,"common_team_count":5,"has_eza":false,"has_sticker":false,"has_super_eza":false},{"id":1020461,"name":"Goku & Vegeta (Angel)","title":"Fused Hope","rarity":5,"element":13,"base_id":1020460,"common_link_count":2,"common_links":[30,60],"common_categories":[58],"is_same_element":true,"is_same_base_element":true,"is_same_element_group":true,"common_team_count":4,"has_eza":true,"has_sticker":false,"has_super_eza":false},{"id":1028421,"name":"Android #18 (Linked State)","title":"Power Boosted through Linking","rarity":4,"element":14,"base_id":1028420,"common_link_count":2,"common_links":[8,60],"common_categories":[37,58,61],"is_same_element":false,"is_same_base_element":false,"is_same_element_group":true,"common_team_count":4,"has_eza":false,"has_sticker":false,"has_super_eza":false},{"id":1017301,"name":"Sealas","title":"Creation of a New History","rarity":4,"element":23,"base_id":1017300,"common_link_count":2,"common_links":[8,60],"common_categories":[42,58,61],"is_same_element":false,"is_same_base_element":true,"is_same_element_group":false,"common_team_count":4,"has_eza":true,"has_sticker":true,"has_super_eza":false},{"id":1025471,"name":"Paikuhan","title":"Blazing Gale","rarity":4,"element":10,"base_id":1025470,"common_link_count":2,"common_links":[30,60],"common_categories":[37,58,71],"is_same_element":false,"is_same_base_element":false,"is_same_element_group":true,"common_team_count":4,"has_eza":true,"has_sticker":true,"has_super_eza":false},{"id":1022311,"name":"Piccolo & Krillin","title":"Teamwork for Victory","rarity":4,"element":13,"base_id":1022310,"common_link_count":2,"common_links":[30,60],"common_categories":[58],"is_same_element":true,"is_same_base_element":true,"is_same_element_group":true,"common_team_count":4,"has_eza":false,"has_sticker":false,"has_super_eza":false},{"id":1021971,"name":"Tapion & Minotia","title":"True Heroes","rarity":5,"element":13,"base_id":1021970,"common_link_count":2,"common_links":[8,30],"common_categories":[71],"is_same_element":true,"is_same_base_element":true,"is_same_element_group":true,"common_team_count":4,"has_eza":false,"has_sticker":false,"has_super_eza":false}],"sa_level_cards":[],"finish_skills":[],"standby_skills":[]}