{"card":{"id":1009851,"name":"Master Roshi (Santa)","character_id":664,"character_size":4,"cost":99,"rarity":4,"hp_init":1,"hp_max":1,"atk_init":1,"atk_max":1,"def_init":1,"def_max":1,"element":11,"special_motion":0,"leader_skill_set_id":100985,"eball_mod_min":40,"eball_mod_num100":5,"eball_mod_mid":0,"eball_mod_mid_num":0,"eball_mod_max":140,"eball_mod_max_num":12,"open_at":"2016-12-21 06:30:00","title":"Thrilling Christmas Eve","leader_skill":"Guarantees Super Attack to level up by 1 \nin Training","skill_level_max":10,"is_f2p":false,"unique_info_id":314,"is_dokkan_fes":false,"is_carnival_only":false},"categories":[],"specials":[{"id":165,"name":"None","description":"None","aim_target":0,"increase_rate":0,"lv_bonus":0,"style":"Normal","lv_start":0,"eball_num_start":12,"card_costume_condition_id":0,"special_view_id":1846,"special_view_id_has_ko":false,"bonus_view_id_1":0,"bonus_view_id_2":0,"bonus_view_id_1_has_ko":false,"bonus_view_id_2_has_ko":false,"special_bonus_1_lv":0,"special_bonus_2_lv":0}],"awakening_routes":[{"awaked_card_id":1009851,"awaked_card":{"id":1009851,"name":"Master Roshi (Santa)","title":"Thrilling Christmas Eve","element":11,"rarity":4,"open_at":"2016-12-21 06:30:00","base_id":1009850,"awaken_items":null,"awaken_cost":0}}],"transformations":[{"next_card_id":1009851,"next_card":{"id":1009851,"name":"Master Roshi (Santa)","rarity":4,"element":11,"open_at":"2016-12-21 06:30:00","base_id":1009850}}],"costumes":[],"card_links":[],"partners":[],"sa_level_cards":[],"finish_skills":[],"standby_skills":[]}