{"card":{"id":1021871,"name":"Krillin","character_id":412,"character_size":4,"cost":40,"rarity":4,"hp_init":2654,"hp_max":8658,"atk_init":2802,"atk_max":9374,"def_init":1464,"def_max":4733,"element":11,"special_motion":3,"passive_skill_set_id":2393,"potential_board_id":21,"leader_skill_set_id":102187,"eball_mod_min":40,"eball_mod_num100":4,"eball_mod_mid":0,"eball_mod_mid_num":0,"eball_mod_max":140,"eball_mod_max_num":12,"open_at":"2021-06-01 06:30:00","title":"Frontline Courage","leader_skill":"\"Saviors\" Category \nKi +3 and HP, ATK & DEF +120%","passive_skill_name":"Rapid Adaptation","passive_skill_desc":"ATK & DEF +120%; \nSuper Class allies' Ki +2 and ATK & DEF +30%; \nplus an additional Ki +2 and ATK & DEF +30% \nfor Super Class allies, an additional ATK +120% and \nreduces damage received by 30% when there is \nan ally whose name includes \"Trunks (Kid)\" or \n\"Goten (Kid)\" attacking in the same turn; \nplus an additional damage reduction of 10% and \nSuper Class allies' chance of performing a critical hit +10% \nwhen there is a \"Movie Bosses\" Category enemy","skill_level_max":10,"is_f2p":false,"unique_info_id":9,"is_dokkan_fes":false,"is_carnival_only":false,"passive_skill_itemized_desc":"*Basic effect(s)*\n- ATK & DEF 120%{passiveImg:up_g}\n- Super Class allies' Ki +2 and ATK & DEF 30%{passiveImg:up_g}\n*When there is an ally whose name includes \"Trunks (Kid)\" or\n\"Goten (Kid)\" attacking in the same turn*\n- ATK 120%{passiveImg:up_g}\n- Damage reduction rate 30%{passiveImg:up_g}\n- Super Class allies' Ki +2 and ATK & DEF 30%{passiveImg:up_g}\n*When there is a \"Movie Bosses\" Category enemy*\n- Damage reduction rate 10%{passiveImg:up_g}\n- Super Class allies' chance of performing a critical hit 10%{passiveImg:up_g}"},"categories":[{"id":9,"name":"Majin Buu Saga","priority":89700},{"id":29,"name":"Movie Heroes","priority":39300},{"id":39,"name":"Kamehameha","priority":69200},{"id":51,"name":"Earthlings","priority":79800},{"id":57,"name":"Saviors","priority":29100},{"id":58,"name":"Battle of Wits","priority":19100},{"id":65,"name":"Turtle School","priority":39100},{"id":79,"name":"Bond of Friendship","priority":49600},{"id":89,"name":"Earth-Bred Fighters","priority":30000},{"id":95,"name":"Earth-Protecting Heroes","priority":20100}],"potential":[{"atk":2000,"def":2000,"hp":2000},{"atk":4100,"def":3700,"hp":3300},{"atk":4400,"def":4000,"hp":3600},{"atk":5100,"def":4310,"hp":3910},{"atk":5400,"def":5000,"hp":4600}],"specials":[{"id":2968,"name":"Kamehameha","description":"Raises DEF for 1 turn and \ncauses supreme damage to enemy","aim_target":0,"increase_rate":150,"lv_bonus":20,"style":"Normal","lv_start":0,"eball_num_start":12,"card_costume_condition_id":0,"special_view_id":7935,"special_view_id_has_ko":false,"bonus_view_id_1":0,"bonus_view_id_2":0,"bonus_view_id_1_has_ko":false,"bonus_view_id_2_has_ko":false,"special_bonus_1_lv":0,"special_bonus_2_lv":0}],"awakening_routes":[{"awaked_card_id":1021860,"awaked_card":{"id":1021860,"name":"Krillin","title":"Comrade's Intuition","element":1,"rarity":3,"open_at":"2021-06-01 06:30:00","base_id":1021860,"awaken_items":null,"awaken_cost":0}},{"card_id":1021860,"awaked_card_id":1021861,"awaked_card":{"type":"CardAwakeningRoute::Zet","id":1021861,"name":"Krillin","title":"Comrade's Intuition","element":11,"rarity":4,"open_at":"2021-06-01 06:30:00","base_id":1021860,"awaken_items":[{"item_id":1,"quantity":50,"rarity":0,"name":"Gregory","description":"A common, easily obtained Awakening Medal.","zeni":500},{"item_id":4,"quantity":20,"rarity":1,"name":"Mr. Popo","description":"A Medal required primarily for TEQ Awakening.\nRelatively easy to get.","zeni":5000},{"item_id":11,"quantity":10,"rarity":2,"name":"Babidi","description":"A Medal required primarily for TEQ Awakening.\nSomewhat difficult to get.","zeni":50000},{"item_id":18,"quantity":3,"rarity":3,"name":"North Kai","description":"A Medal required primarily for TEQ Awakening.\nDifficult to get.","zeni":250000},{"item_id":19,"quantity":1,"rarity":3,"name":"Supreme Kai","description":"The ultimate, rarely obtainable Awakening Medal.","zeni":500000}],"awaken_cost":1875000}},{"card_id":1021861,"awaked_card_id":1021871,"awaked_card":{"type":"CardAwakeningRoute::Dokkan","id":1021871,"name":"Krillin","title":"Frontline Courage","element":11,"rarity":4,"open_at":"2021-06-01 06:30:00","base_id":1021870,"awaken_items":[{"item_id":5641,"quantity":35,"rarity":3,"name":"Super Saiyan Trunks (Kid) & Super Saiyan Goten (Kid)","description":"Character-specific Medal required for Awakening.","zeni":20000}],"awaken_cost":700000}}],"transformations":[{"next_card_id":1021871,"next_card":{"id":1021871,"name":"Krillin","rarity":4,"element":11,"open_at":"2021-06-01 06:30:00","base_id":1021870}}],"costumes":[],"card_links":[{"idx":1,"link_skill_id":36,"name":"Turtle School","level1_description":"ATK & DEF +10%","level10_description":"Ki +2 and ATK & DEF +20%"},{"idx":2,"link_skill_id":30,"name":"Experienced Fighters","level1_description":"ATK +10%","level10_description":"ATK +15%"},{"idx":3,"link_skill_id":2,"name":"Courage","level1_description":"Ki +1","level10_description":"Ki +2 and ATK +10%"},{"idx":4,"link_skill_id":1,"name":"High Compatibility","level1_description":"Ki +1","level10_description":"Ki +2 and ATK & DEF +10%"},{"idx":5,"link_skill_id":37,"name":"Solid Support","level1_description":"ATK +10% and all enemies' DEF -15%","level10_description":"ATK +15% and all enemies' DEF -20%"},{"idx":6,"link_skill_id":47,"name":"Kamehameha","level1_description":"ATK +5% when performing a Super Attack","level10_description":"ATK +10% when performing a Super Attack"},{"idx":7,"link_skill_id":109,"name":"Fierce Battle","level1_description":"ATK +15%","level10_description":"ATK +20%"}],"partners":[{"id":1028471,"name":"Krillin & Android #18","title":"Adversity-Shattering Allies","rarity":4,"element":10,"base_id":1028470,"common_link_count":5,"common_links":[2,30,36,37,109],"common_categories":[29,58],"is_same_element":false,"is_same_base_element":false,"is_same_element_group":true,"common_team_count":3,"has_eza":false,"has_sticker":false,"has_super_eza":false},{"id":1024971,"name":"Krillin & Gohan (Youth)","title":"Strength Concentrated on the Fists","rarity":4,"element":11,"base_id":1024970,"common_link_count":4,"common_links":[2,37,47,109],"common_categories":[29,58,89],"is_same_element":true,"is_same_base_element":true,"is_same_element_group":true,"common_team_count":6,"has_eza":false,"has_sticker":false,"has_super_eza":false},{"id":1022881,"name":"Krillin/Vegeta","title":"Strategy to Defeat the Emperor","rarity":4,"element":12,"base_id":1022880,"common_link_count":4,"common_links":[1,2,36,37],"common_categories":[51,58,65,79,89],"is_same_element":false,"is_same_base_element":false,"is_same_element_group":true,"common_team_count":6,"has_eza":true,"has_sticker":true,"has_super_eza":false},{"id":1020281,"name":"Tien","title":"Risky Covering Fire","rarity":4,"element":14,"base_id":1020280,"common_link_count":4,"common_links":[2,30,37,109],"common_categories":[9,51,57,79,89],"is_same_element":false,"is_same_base_element":false,"is_same_element_group":true,"common_team_count":6,"has_eza":false,"has_sticker":false,"has_super_eza":false},{"id":1025801,"name":"Yamcha","title":"Earth's Dominant Elite","rarity":4,"element":12,"base_id":1025800,"common_link_count":4,"common_links":[36,37,47,109],"common_categories":[39,51,65,89],"is_same_element":false,"is_same_base_element":false,"is_same_element_group":true,"common_team_count":5,"has_eza":false,"has_sticker":true,"has_super_eza":false},{"id":1012461,"name":"Tapion","title":"Hero on a Mission","rarity":4,"element":11,"base_id":1012460,"common_link_count":4,"common_links":[2,30,37,109],"common_categories":[29],"is_same_element":true,"is_same_base_element":true,"is_same_element_group":true,"common_team_count":4,"has_eza":true,"has_sticker":true,"has_super_eza":false},{"id":1030431,"name":"Super Saiyan Goku + Super Saiyan Vegeta (Angel)","title":"Incomparable Radiance","rarity":5,"element":11,"base_id":1030430,"common_link_count":3,"common_links":[30,47,109],"common_categories":[9,39,58,65,79,89,95],"is_same_element":true,"is_same_base_element":true,"is_same_element_group":true,"common_team_count":10,"has_eza":false,"has_sticker":false,"has_super_eza":false},{"id":4026261,"name":"Super Saiyan Goku","title":"Fighter Entrusted with Allies' Wishes","rarity":4,"element":14,"base_id":4026260,"common_link_count":3,"common_links":[30,47,109],"common_categories":[29,39,65,79,89,95],"is_same_element":false,"is_same_base_element":false,"is_same_element_group":true,"common_team_count":7,"has_eza":false,"has_sticker":false,"has_super_eza":false},{"id":1016571,"name":"Goku (Youth)","title":"All-Or-Nothing Punch","rarity":4,"element":12,"base_id":1016570,"common_link_count":3,"common_links":[36,47,109],"common_categories":[39,57,65,79,89,95],"is_same_element":false,"is_same_base_element":false,"is_same_element_group":true,"common_team_count":7,"has_eza":true,"has_sticker":true,"has_super_eza":false},{"id":1007321,"name":"Yamcha","title":"Absolute Loss","rarity":4,"element":11,"base_id":1007320,"common_link_count":3,"common_links":[36,37,47],"common_categories":[39,51,65,89],"is_same_element":true,"is_same_base_element":true,"is_same_element_group":true,"common_team_count":7,"has_eza":false,"has_sticker":false,"has_super_eza":false},{"id":1029141,"name":"Master Roshi","title":"Next-Generation-Guiding Turtle School","rarity":4,"element":13,"base_id":1029140,"common_link_count":3,"common_links":[36,47,109],"common_categories":[39,51,58,65,89],"is_same_element":false,"is_same_base_element":false,"is_same_element_group":true,"common_team_count":6,"has_eza":false,"has_sticker":true,"has_super_eza":false},{"id":1021351,"name":"Ultimate Gohan & Piccolo","title":"Bond Forged by Master and Disciple","rarity":4,"element":11,"base_id":1021350,"common_link_count":3,"common_links":[37,47,109],"common_categories":[39,58,89],"is_same_element":true,"is_same_base_element":true,"is_same_element_group":true,"common_team_count":6,"has_eza":false,"has_sticker":false,"has_super_eza":false},{"id":1010941,"name":"Paikuhan","title":"Clever Strategy","rarity":4,"element":11,"base_id":1010940,"common_link_count":3,"common_links":[30,37,109],"common_categories":[57,58],"is_same_element":true,"is_same_base_element":true,"is_same_element_group":true,"common_team_count":5,"has_eza":true,"has_sticker":true,"has_super_eza":false},{"id":1022121,"name":"Goku & Piccolo","title":"Rivals Acting in Concert","rarity":5,"element":12,"base_id":1022120,"common_link_count":3,"common_links":[30,37,109],"common_categories":[29,57,89,95],"is_same_element":false,"is_same_base_element":false,"is_same_element_group":true,"common_team_count":5,"has_eza":false,"has_sticker":false,"has_super_eza":false},{"id":1014761,"name":"Super Saiyan Goku","title":"Boiling Power","rarity":4,"element":10,"base_id":1014760,"common_link_count":3,"common_links":[30,47,109],"common_categories":[39,65,79,89],"is_same_element":false,"is_same_base_element":false,"is_same_element_group":true,"common_team_count":5,"has_eza":true,"has_sticker":true,"has_super_eza":false},{"id":4014771,"name":"Super Saiyan 2 Goku","title":"Boiling Power","rarity":4,"element":10,"base_id":4014770,"common_link_count":3,"common_links":[30,47,109],"common_categories":[39,65,79,89],"is_same_element":false,"is_same_base_element":false,"is_same_element_group":true,"common_team_count":5,"has_eza":true,"has_sticker":false,"has_super_eza":false},{"id":4014781,"name":"Super Saiyan 3 Goku","title":"Boiling Power","rarity":4,"element":10,"base_id":4014780,"common_link_count":3,"common_links":[30,47,109],"common_categories":[39,65,79,89],"is_same_element":false,"is_same_base_element":false,"is_same_element_group":true,"common_team_count":5,"has_eza":true,"has_sticker":false,"has_super_eza":false},{"id":4030541,"name":"Goku + Frieza (Final Form) (Angel)","title":"Universe 7's Final Will to Fight","rarity":5,"element":22,"base_id":4030540,"common_link_count":3,"common_links":[30,47,109],"common_categories":[39,65,79,89],"is_same_element":false,"is_same_base_element":false,"is_same_element_group":false,"common_team_count":4,"has_eza":false,"has_sticker":false,"has_super_eza":false},{"id":1030081,"name":"Yamcha","title":"Confidence-Boosting Martial Arts","rarity":4,"element":13,"base_id":1030080,"common_link_count":3,"common_links":[2,36,37],"common_categories":[51,65,89],"is_same_element":false,"is_same_base_element":false,"is_same_element_group":true,"common_team_count":4,"has_eza":false,"has_sticker":false,"has_super_eza":false},{"id":1029771,"name":"Piccolo/Super Saiyan Vegeta","title":"Resolve to Challenge Powerful Foes","rarity":4,"element":14,"base_id":1029770,"common_link_count":3,"common_links":[30,37,109],"common_categories":[29,58,89],"is_same_element":false,"is_same_base_element":false,"is_same_element_group":true,"common_team_count":4,"has_eza":false,"has_sticker":false,"has_super_eza":false},{"id":1017061,"name":"Mai (Future)","title":"Power to Overcome Adversity","rarity":4,"element":12,"base_id":1017060,"common_link_count":3,"common_links":[2,37,109],"common_categories":[51,58,89],"is_same_element":false,"is_same_base_element":false,"is_same_element_group":true,"common_team_count":4,"has_eza":true,"has_sticker":true,"has_super_eza":false},{"id":1027371,"name":"Mai (Future)","title":"Counterattack of Humanity's Survivors","rarity":4,"element":13,"base_id":1027370,"common_link_count":3,"common_links":[2,37,109],"common_categories":[51,58,89],"is_same_element":false,"is_same_base_element":false,"is_same_element_group":true,"common_team_count":4,"has_eza":false,"has_sticker":false,"has_super_eza":false},{"id":1025311,"name":"Super Full Power Saiyan 4 Limit Breaker Goku (Xeno)","title":"Breaking Limits for Victory","rarity":4,"element":12,"base_id":1025310,"common_link_count":3,"common_links":[30,47,109],"common_categories":[39,65,89],"is_same_element":false,"is_same_base_element":false,"is_same_element_group":true,"common_team_count":4,"has_eza":false,"has_sticker":false,"has_super_eza":false},{"id":1024951,"name":"Piccolo","title":"Valiant Confrontation","rarity":4,"element":13,"base_id":1024950,"common_link_count":3,"common_links":[30,37,109],"common_categories":[29,58,89],"is_same_element":false,"is_same_base_element":false,"is_same_element_group":true,"common_team_count":4,"has_eza":false,"has_sticker":false,"has_super_eza":false},{"id":1012901,"name":"Super Saiyan Goku & Super Saiyan Vegeta","title":"Fused Super Power","rarity":5,"element":12,"base_id":1012900,"common_link_count":3,"common_links":[30,47,109],"common_categories":[9,39,58],"is_same_element":false,"is_same_base_element":false,"is_same_element_group":true,"common_team_count":4,"has_eza":true,"has_sticker":false,"has_super_eza":false}],"sa_level_cards":[{"id":1030051,"name":"Krillin","title":"A Fighter's Sense of Responsibility","rarity":4,"element":12,"base_id":1030050,"has_eza":false,"is_f2p":true,"level_up_chance":100},{"id":1028991,"name":"Krillin","title":"Spirited Bald Fighter","rarity":4,"element":10,"base_id":1028990,"has_eza":false,"is_f2p":true,"level_up_chance":100},{"id":1026571,"name":"Krillin","title":"Hard-Working Martial Artist","rarity":4,"element":13,"base_id":1026570,"has_eza":false,"is_f2p":false,"level_up_chance":100},{"id":1022871,"name":"Krillin","title":"Preparations Made Before the Final Battle","rarity":4,"element":12,"base_id":1022870,"has_eza":false,"is_f2p":true,"level_up_chance":100},{"id":1020021,"name":"Krillin","title":"A Veteran's Ingenuity and Perseverance","rarity":4,"element":10,"base_id":1020020,"has_eza":false,"is_f2p":false,"level_up_chance":100},{"id":1019511,"name":"Krillin","title":"Spirited Earth Defense","rarity":4,"element":14,"base_id":1019510,"has_eza":false,"is_f2p":true,"level_up_chance":100},{"id":1017811,"name":"Krillin","title":"Ready to Fight","rarity":4,"element":12,"base_id":1017810,"has_eza":false,"is_f2p":true,"level_up_chance":100},{"id":1004531,"name":"Krillin","title":"Reliable Helper","rarity":4,"element":11,"base_id":1004530,"has_eza":false,"is_f2p":true,"level_up_chance":100},{"id":1002931,"name":"Krillin","title":"Polished Technique","rarity":4,"element":13,"base_id":1002930,"has_eza":false,"is_f2p":true,"level_up_chance":100},{"id":1013311,"name":"Krillin","title":"Hard-Fought Match","rarity":3,"element":11,"base_id":1013310,"has_eza":false,"is_f2p":false,"level_up_chance":50},{"id":1007901,"name":"Krillin","title":"Heartening Support","rarity":3,"element":14,"base_id":1007900,"has_eza":false,"is_f2p":true,"level_up_chance":50},{"id":1004461,"name":"Krillin","title":"Danger Sense","rarity":3,"element":12,"base_id":1004460,"has_eza":false,"is_f2p":false,"level_up_chance":50},{"id":1000891,"name":"Krillin","title":"Martial Stability","rarity":3,"element":11,"base_id":1000890,"has_eza":false,"is_f2p":false,"level_up_chance":50},{"id":1000111,"name":"Krillin","title":"Fruits of Labor","rarity":3,"element":11,"base_id":1000110,"has_eza":false,"is_f2p":false,"level_up_chance":50},{"id":1003911,"name":"Krillin","title":"Acclaimed Ability","rarity":2,"element":13,"resource_id":1001880,"base_id":1003910,"has_eza":false,"is_f2p":false,"level_up_chance":5},{"id":1001681,"name":"Krillin","title":"Wisdom and Experience","rarity":2,"element":10,"base_id":1001680,"has_eza":false,"is_f2p":false,"level_up_chance":5},{"id":1001161,"name":"Krillin","title":"Passionate Friendship","rarity":2,"element":13,"base_id":1001160,"has_eza":false,"is_f2p":false,"level_up_chance":5},{"id":1000291,"name":"Krillin","title":"Competitive Comrades","rarity":2,"element":14,"base_id":1000290,"has_eza":false,"is_f2p":false,"level_up_chance":5}],"finish_skills":[],"standby_skills":[]}