{"card":{"id":1021721,"name":"Super Saiyan Trunks (Teen)","character_id":646,"character_size":4,"cost":40,"rarity":4,"hp_init":2740,"hp_max":9042,"atk_init":2693,"atk_max":8890,"def_init":1602,"def_max":5289,"element":13,"special_motion":1,"passive_skill_set_id":2387,"potential_board_id":23,"leader_skill_set_id":102172,"eball_mod_min":40,"eball_mod_num100":3,"eball_mod_mid":0,"eball_mod_mid_num":0,"eball_mod_max":140,"eball_mod_max_num":12,"open_at":"2021-03-18 06:18:00","title":"Counterattack of Light","leader_skill":"\"Hybrid Saiyans\" Category \nKi +4 and HP, ATK & DEF +120%","passive_skill_name":"Royal Bloodline","passive_skill_desc":"ATK & DEF +200% and medium chance of \nlaunching an additional Super Attack; \n\"Hybrid Saiyans\" Category allies' \nKi +3 and ATK & DEF +40%","skill_level_max":10,"is_f2p":false,"unique_info_id":113,"is_dokkan_fes":false,"is_carnival_only":false,"passive_skill_itemized_desc":"*Basic effect(s)*\n- ATK & DEF 200%{passiveImg:up_g}\n- Medium chance of launching an additional Super Attack\n- \"Hybrid Saiyans\" Category allies' Ki +3 and ATK & DEF\n40%{passiveImg:up_g}"},"categories":[{"id":5,"name":"Hybrid Saiyans","priority":79900},{"id":19,"name":"Future Saga","priority":89600},{"id":26,"name":"Time Travelers","priority":29500},{"id":29,"name":"Movie Heroes","priority":39300},{"id":31,"name":"Vegeta's Family","priority":79300},{"id":36,"name":"Super Saiyans","priority":70000},{"id":40,"name":"Bond of Master and Disciple","priority":49500},{"id":58,"name":"Battle of Wits","priority":19100},{"id":81,"name":"Entrusted Will","priority":19300},{"id":89,"name":"Earth-Bred Fighters","priority":30000}],"potential":[{"atk":2000,"def":2000,"hp":2000},{"atk":4100,"def":3300,"hp":3700},{"atk":4400,"def":3600,"hp":4000},{"atk":5100,"def":3910,"hp":4310},{"atk":5400,"def":4600,"hp":5000}],"specials":[{"id":2956,"name":"Burning Attack","description":"Raises ATK & DEF for 1 turn and \ncauses supreme damage with \na medium chance of stunning the enemy","aim_target":0,"increase_rate":150,"lv_bonus":20,"style":"Normal","lv_start":0,"eball_num_start":12,"card_costume_condition_id":0,"special_category_id":1,"special_category_name":"Ki Blast","special_view_id":7907,"special_view_id_has_ko":false,"bonus_view_id_1":0,"bonus_view_id_2":0,"bonus_view_id_1_has_ko":false,"bonus_view_id_2_has_ko":false,"special_bonus_1_lv":0,"special_bonus_2_lv":0},{"id":2957,"name":"Double Masenko","description":"Greatly raises ATK for 1 turn, raises DEF \nand causes immense damage with \na high chance of stunning the enemy","causality_description":"Activated when there is an ally \nwhose name includes \"Gohan (Youth)\" \nattacking in the same turn","aim_target":0,"increase_rate":180,"lv_bonus":25,"style":"Condition","lv_start":0,"eball_num_start":12,"card_costume_condition_id":0,"special_category_id":1,"special_category_name":"Ki Blast","special_view_id":7909,"special_view_id_has_ko":false,"bonus_view_id_1":0,"bonus_view_id_2":0,"bonus_view_id_1_has_ko":false,"bonus_view_id_2_has_ko":false,"special_bonus_1_lv":0,"special_bonus_2_lv":0}],"awakening_routes":[{"awaked_card_id":1021710,"awaked_card":{"id":1021710,"name":"Trunks (Teen)","title":"Courageous Punch","element":3,"rarity":3,"open_at":"2021-03-18 06:18:00","base_id":1021710,"awaken_items":null,"awaken_cost":0}},{"card_id":1021710,"awaked_card_id":1021711,"awaked_card":{"type":"CardAwakeningRoute::Zet","id":1021711,"name":"Trunks (Teen)","title":"Courageous Punch","element":13,"rarity":4,"open_at":"2021-03-18 06:18:00","base_id":1021710,"awaken_items":[{"item_id":1,"quantity":50,"rarity":0,"name":"Gregory","description":"A common, easily obtained Awakening Medal.","zeni":500},{"item_id":6,"quantity":20,"rarity":1,"name":"Master Roshi","description":"A Medal required primarily for STR Awakening.\nRelatively easy to get.","zeni":5000},{"item_id":12,"quantity":10,"rarity":2,"name":"Bibidi","description":"A Medal required primarily for STR Awakening.\nSomewhat difficult to get.","zeni":50000},{"item_id":16,"quantity":3,"rarity":3,"name":"South Kai","description":"A Medal required primarily for STR Awakening.\nDifficult to get.","zeni":250000},{"item_id":20,"quantity":1,"rarity":3,"name":"Elder Kai","description":"The ultimate, rarely obtainable Awakening Medal.","zeni":500000}],"awaken_cost":1875000}},{"card_id":1021711,"awaked_card_id":1021721,"awaked_card":{"type":"CardAwakeningRoute::Dokkan","id":1021721,"name":"Super Saiyan Trunks (Teen)","title":"Counterattack of Light","element":13,"rarity":4,"open_at":"2021-03-18 06:18:00","base_id":1021720,"awaken_items":[{"item_id":5012,"quantity":35,"rarity":3,"name":"Super Saiyan Broly","description":"Character-specific Medal required for Awakening.","zeni":20000}],"awaken_cost":700000}}],"transformations":[{"next_card_id":1021721,"next_card":{"id":1021721,"name":"Super Saiyan Trunks (Teen)","rarity":4,"element":13,"open_at":"2021-03-18 06:18:00","base_id":1021720}}],"costumes":[],"card_links":[{"idx":1,"link_skill_id":19,"name":"Messenger from the Future","level1_description":"ATK +5%","level10_description":"ATK +10%"},{"idx":2,"link_skill_id":29,"name":"Super Saiyan","level1_description":"ATK +10%","level10_description":"ATK +15%"},{"idx":3,"link_skill_id":9,"name":"Golden Warrior","level1_description":"All enemies' DEF -5% and Ki +1","level10_description":"All enemies' DEF -10% and Ki +1"},{"idx":4,"link_skill_id":39,"name":"Cold Judgment","level1_description":"DEF +20%","level10_description":"DEF +25%"},{"idx":5,"link_skill_id":40,"name":"Royal Lineage","level1_description":"Ki +1","level10_description":"Ki +2 and ATK +5%"},{"idx":6,"link_skill_id":66,"name":"Dismal Future","level1_description":"Ki +1","level10_description":"Ki +2 and chance of \nperforming a critical hit +5%"},{"idx":7,"link_skill_id":109,"name":"Fierce Battle","level1_description":"ATK +15%","level10_description":"ATK +20%"}],"partners":[{"id":1018151,"name":"Super Saiyan Trunks (Future)","title":"Victor of the Future","rarity":4,"element":11,"base_id":1018150,"common_link_count":7,"common_links":[9,19,29,39,40,66,109],"common_categories":[5,19,26,31,36,40,58,81,89],"is_same_element":false,"is_same_base_element":false,"is_same_element_group":true,"common_team_count":10,"has_eza":true,"has_sticker":true,"has_super_eza":false},{"id":1012961,"name":"Super Saiyan Trunks (Future)","title":"Unwavering Conviction","rarity":4,"element":13,"base_id":1012960,"common_link_count":6,"common_links":[9,19,29,40,66,109],"common_categories":[5,19,26,31,36,40,58,81,89],"is_same_element":true,"is_same_base_element":true,"is_same_element_group":true,"common_team_count":12,"has_eza":true,"has_sticker":true,"has_super_eza":false},{"id":1008871,"name":"Super Saiyan Trunks (Future)","title":"Humanity's Hope","rarity":4,"element":11,"base_id":1008870,"common_link_count":6,"common_links":[9,19,29,40,66,109],"common_categories":[5,19,26,31,36,40,58,81,89],"is_same_element":false,"is_same_base_element":false,"is_same_element_group":true,"common_team_count":10,"has_eza":true,"has_sticker":true,"has_super_eza":false},{"id":1009581,"name":"Super Saiyan Trunks (Future)","title":"Blade of Hope and Dreams","rarity":4,"element":12,"base_id":1009580,"common_link_count":6,"common_links":[9,19,29,40,66,109],"common_categories":[5,19,26,31,36,40,58,81,89],"is_same_element":false,"is_same_base_element":false,"is_same_element_group":true,"common_team_count":10,"has_eza":true,"has_sticker":true,"has_super_eza":false},{"id":4017091,"name":"Super Saiyan Trunks (Future)","title":"Resilient Will to Protect the Future","rarity":4,"element":11,"base_id":4017090,"common_link_count":6,"common_links":[9,19,29,40,66,109],"common_categories":[5,19,26,31,36,40,58,81,89],"is_same_element":false,"is_same_base_element":false,"is_same_element_group":true,"common_team_count":10,"has_eza":true,"has_sticker":false,"has_super_eza":false},{"id":4017101,"name":"Super Saiyan Trunks (Future)","title":"Resilient Will to Protect the Future","rarity":4,"element":11,"base_id":4017100,"common_link_count":6,"common_links":[9,19,29,40,66,109],"common_categories":[5,19,26,31,36,40,58,81,89],"is_same_element":false,"is_same_base_element":false,"is_same_element_group":true,"common_team_count":10,"has_eza":true,"has_sticker":false,"has_super_eza":false},{"id":1028981,"name":"Super Saiyan 2 Trunks (Future)","title":"Battle to Defend the Dignity of Mankind","rarity":4,"element":10,"base_id":1028980,"common_link_count":6,"common_links":[9,19,29,40,66,109],"common_categories":[5,19,26,31,40,58,81,89],"is_same_element":false,"is_same_base_element":false,"is_same_element_group":true,"common_team_count":9,"has_eza":false,"has_sticker":false,"has_super_eza":false},{"id":1027351,"name":"Super Saiyan Trunks (Future)","title":"Readiness to Defy a God","rarity":4,"element":13,"base_id":1027350,"common_link_count":5,"common_links":[9,19,29,40,66],"common_categories":[5,19,26,31,36,40,58,81,89],"is_same_element":true,"is_same_base_element":true,"is_same_element_group":true,"common_team_count":12,"has_eza":true,"has_sticker":true,"has_super_eza":false},{"id":1009781,"name":"Super Trunks","title":"Confident of Victory","rarity":4,"element":13,"base_id":1009780,"common_link_count":5,"common_links":[9,19,29,40,109],"common_categories":[5,19,26,31,36,40,81,89],"is_same_element":true,"is_same_base_element":true,"is_same_element_group":true,"common_team_count":11,"has_eza":true,"has_sticker":true,"has_super_eza":false},{"id":1027291,"name":"Super Saiyan Trunks (Future)","title":"Hope at the End of a Deadly Showdown","rarity":5,"element":14,"base_id":1027290,"common_link_count":5,"common_links":[9,29,40,66,109],"common_categories":[5,19,26,31,36,40,58,81,89],"is_same_element":false,"is_same_base_element":false,"is_same_element_group":true,"common_team_count":10,"has_eza":false,"has_sticker":false,"has_super_eza":false},{"id":4027301,"name":"Super Saiyan Trunks (Future)","title":"Hope at the End of a Deadly Showdown","rarity":5,"element":14,"base_id":4027300,"common_link_count":5,"common_links":[9,29,40,66,109],"common_categories":[5,19,26,31,36,40,58,81,89],"is_same_element":false,"is_same_base_element":false,"is_same_element_group":true,"common_team_count":10,"has_eza":false,"has_sticker":false,"has_super_eza":false},{"id":1014051,"name":"Super Saiyan Trunks (Future)","title":"Alternate Ending","rarity":5,"element":10,"base_id":1014050,"common_link_count":5,"common_links":[19,29,39,40,66],"common_categories":[5,19,26,31,36,40,58,81,89],"is_same_element":false,"is_same_base_element":false,"is_same_element_group":true,"common_team_count":10,"has_eza":true,"has_sticker":false,"has_super_eza":false},{"id":4023121,"name":"Super Saiyan Trunks (Teen)","title":"Fate-Changing Messenger","rarity":4,"element":10,"base_id":4023120,"common_link_count":5,"common_links":[19,29,39,40,109],"common_categories":[5,19,26,31,36,40,58,81,89],"is_same_element":false,"is_same_base_element":false,"is_same_element_group":true,"common_team_count":10,"has_eza":false,"has_sticker":false,"has_super_eza":false},{"id":1011191,"name":"Super Saiyan Trunks (Future)","title":"To a New Future","rarity":4,"element":12,"base_id":1011190,"common_link_count":5,"common_links":[9,29,40,66,109],"common_categories":[5,19,26,31,36,40,58,81,89],"is_same_element":false,"is_same_base_element":false,"is_same_element_group":true,"common_team_count":10,"has_eza":true,"has_sticker":true,"has_super_eza":false},{"id":1009701,"name":"Super Saiyan Trunks (Future)","title":"A Will Beyond Time","rarity":4,"element":14,"base_id":1009700,"common_link_count":5,"common_links":[9,19,29,40,66],"common_categories":[5,19,26,31,36,40,58,81,89],"is_same_element":false,"is_same_base_element":false,"is_same_element_group":true,"common_team_count":10,"has_eza":true,"has_sticker":true,"has_super_eza":false},{"id":4027011,"name":"Super Trunks","title":"Super Power Counterattack","rarity":4,"element":11,"base_id":4027010,"common_link_count":5,"common_links":[9,19,29,40,109],"common_categories":[5,19,26,31,36,40,81,89],"is_same_element":false,"is_same_base_element":false,"is_same_element_group":true,"common_team_count":9,"has_eza":false,"has_sticker":false,"has_super_eza":false},{"id":1009771,"name":"Super Trunks","title":"Convergent Fury","rarity":4,"element":14,"base_id":1009770,"common_link_count":5,"common_links":[9,19,29,40,109],"common_categories":[5,19,26,31,36,40,81,89],"is_same_element":false,"is_same_base_element":false,"is_same_element_group":true,"common_team_count":9,"has_eza":true,"has_sticker":true,"has_super_eza":false},{"id":1010021,"name":"Super Saiyan Trunks (GT)","title":"Brains and Brawn Combined","rarity":4,"element":13,"base_id":1010020,"common_link_count":5,"common_links":[9,29,39,40,109],"common_categories":[5,31,36,58,89],"is_same_element":true,"is_same_base_element":true,"is_same_element_group":true,"common_team_count":8,"has_eza":false,"has_sticker":false,"has_super_eza":false},{"id":4018131,"name":"Super Saiyan Gohan (Future)","title":"Heroic Warrior","rarity":4,"element":12,"base_id":4018130,"common_link_count":5,"common_links":[9,29,39,66,109],"common_categories":[5,19,36,40,89],"is_same_element":false,"is_same_base_element":false,"is_same_element_group":true,"common_team_count":6,"has_eza":true,"has_sticker":false,"has_super_eza":false},{"id":1016441,"name":"Super Saiyan Trunks (GT)","title":"Confidence-Imbuing Moment","rarity":4,"element":10,"base_id":1016440,"common_link_count":5,"common_links":[9,29,39,40,109],"common_categories":[5,31,36,58,89],"is_same_element":false,"is_same_base_element":false,"is_same_element_group":true,"common_team_count":6,"has_eza":false,"has_sticker":false,"has_super_eza":false},{"id":1018101,"name":"Trunks (Teen)","title":"Magnificent Swordsmanship","rarity":4,"element":14,"base_id":1018100,"common_link_count":4,"common_links":[19,39,40,109],"common_categories":[5,19,26,29,31,40,58,81,89],"is_same_element":false,"is_same_base_element":false,"is_same_element_group":true,"common_team_count":10,"has_eza":true,"has_sticker":true,"has_super_eza":false},{"id":1017081,"name":"Trunks (Teen) (Future)","title":"Resilient Will to Protect the Future","rarity":4,"element":11,"base_id":1017080,"common_link_count":4,"common_links":[19,40,66,109],"common_categories":[5,19,26,31,36,40,58,81,89],"is_same_element":false,"is_same_base_element":false,"is_same_element_group":true,"common_team_count":10,"has_eza":true,"has_sticker":true,"has_super_eza":false},{"id":1023111,"name":"Trunks (Teen)","title":"Fate-Changing Messenger","rarity":4,"element":10,"base_id":1023110,"common_link_count":4,"common_links":[19,39,40,109],"common_categories":[5,19,26,31,36,40,58,81,89],"is_same_element":false,"is_same_base_element":false,"is_same_element_group":true,"common_team_count":10,"has_eza":false,"has_sticker":true,"has_super_eza":false},{"id":1016971,"name":"Trunks (Teen)","title":"Radiant Battle","rarity":4,"element":12,"base_id":1016970,"common_link_count":4,"common_links":[19,39,40,66],"common_categories":[5,19,26,29,31,40,58,81,89],"is_same_element":false,"is_same_base_element":false,"is_same_element_group":true,"common_team_count":10,"has_eza":false,"has_sticker":false,"has_super_eza":false},{"id":1014711,"name":"Super Trunks","title":"Rapid Growth","rarity":4,"element":12,"base_id":1014710,"common_link_count":4,"common_links":[9,19,29,40],"common_categories":[5,19,26,31,36,40,81,89],"is_same_element":false,"is_same_base_element":false,"is_same_element_group":true,"common_team_count":9,"has_eza":true,"has_sticker":true,"has_super_eza":false}],"sa_level_cards":[{"id":1027401,"name":"Trunks (Teen)","title":"Investigation of Dimensional Distortion","rarity":4,"element":11,"base_id":1027400,"has_eza":false,"is_f2p":true,"level_up_chance":100},{"id":1027241,"name":"Trunks (Teen)","title":"Facing a Mysterious Time Machine","rarity":4,"element":12,"base_id":1027240,"has_eza":false,"is_f2p":true,"level_up_chance":100},{"id":1024221,"name":"Trunks (Teen)","title":"At Ease When Back on the Front Line","rarity":4,"element":11,"base_id":1024220,"has_eza":false,"is_f2p":true,"level_up_chance":100},{"id":1023101,"name":"Trunks (Teen)","title":"Intersection of Past and Present","rarity":4,"element":10,"base_id":1023100,"has_eza":false,"is_f2p":false,"level_up_chance":100},{"id":1018091,"name":"Trunks (Teen)","title":"Unwavering Will","rarity":4,"element":14,"base_id":1018090,"has_eza":false,"is_f2p":false,"level_up_chance":100},{"id":1016971,"name":"Trunks (Teen)","title":"Radiant Battle","rarity":4,"element":12,"base_id":1016970,"has_eza":false,"is_f2p":true,"level_up_chance":100},{"id":1011701,"name":"Trunks (Teen)","title":"Mysterious Youth","rarity":4,"element":14,"base_id":1011700,"has_eza":false,"is_f2p":false,"level_up_chance":100},{"id":1006571,"name":"Trunks (Teen)","title":"The Hope Deep Inside","rarity":4,"element":13,"base_id":1006570,"has_eza":false,"is_f2p":true,"level_up_chance":100},{"id":1002891,"name":"Trunks (Teen)","title":"Future Hope","rarity":3,"element":13,"base_id":1002890,"has_eza":false,"is_f2p":true,"level_up_chance":50},{"id":1001861,"name":"Trunks (Teen)","title":"Honed for Battle","rarity":3,"element":14,"base_id":1001860,"has_eza":false,"is_f2p":false,"level_up_chance":50},{"id":1000881,"name":"Trunks (Teen)","title":"Blitz Blade","rarity":3,"element":11,"base_id":1000880,"has_eza":false,"is_f2p":false,"level_up_chance":50},{"id":1000811,"name":"Trunks (Teen)","title":"Messenger from the Future","rarity":3,"element":12,"base_id":1000810,"has_eza":false,"is_f2p":false,"level_up_chance":50},{"id":1000101,"name":"Trunks (Teen)","title":"Hawk Eyes","rarity":3,"element":10,"base_id":1000100,"has_eza":false,"is_f2p":false,"level_up_chance":50},{"id":1000281,"name":"Trunks (Teen)","title":"From Hell and Back","rarity":2,"element":10,"base_id":1000280,"has_eza":false,"is_f2p":false,"level_up_chance":5}],"finish_skills":[],"standby_skills":[]}